MANIFEST.in
VERSION
setup.py
libtensorshield/package.json
libtensorshield.egg-info/PKG-INFO
libtensorshield.egg-info/SOURCES.txt
libtensorshield.egg-info/dependency_links.txt
libtensorshield.egg-info/requires.txt
libtensorshield.egg-info/top_level.txt
libtensorshield/testing/__init__.py
libtensorshield/testing/resources/wallets/miner-a/coldkey
libtensorshield/testing/resources/wallets/miner-a/coldkeypub.txt
libtensorshield/testing/resources/wallets/miner-a/hotkeys/1
libtensorshield/testing/resources/wallets/miner-a/hotkeys/2
libtensorshield/testing/resources/wallets/miner-b/coldkey
libtensorshield/testing/resources/wallets/miner-b/coldkeypub.txt
libtensorshield/testing/resources/wallets/miner-b/hotkeys/1
libtensorshield/testing/resources/wallets/miner-b/hotkeys/2
libtensorshield/testing/resources/wallets/validator-a/coldkey
libtensorshield/testing/resources/wallets/validator-a/coldkeypub.txt
libtensorshield/testing/resources/wallets/validator-a/hotkeys/1
libtensorshield/testing/resources/wallets/validator-a/hotkeys/2
libtensorshield/testing/resources/wallets/validator-b/coldkey
libtensorshield/testing/resources/wallets/validator-b/coldkeypub.txt
libtensorshield/testing/resources/wallets/validator-b/hotkeys/1
libtensorshield/testing/resources/wallets/validator-b/hotkeys/2
libtensorshield/types/__init__.py
libtensorshield/types/_axoninfo.py
libtensorshield/types/_balance.py
libtensorshield/types/_fixedpoint.py
libtensorshield/types/_infobase.py
libtensorshield/types/_neuron.py
libtensorshield/types/_neuroninfo.py
libtensorshield/types/_neuroninfolite.py
libtensorshield/types/_neuronlist.py
libtensorshield/types/_ss58address.py
libtensorshield/utils/__init__.py
tests/unit/test_bittensor_compat.py
tests/unit/test_type_balance.py
tests/unit/test_type_ss58address.py